shipgit/__init__.py
shipgit/permissions.shipgit
shipgit/shipgit.py
shipgit-0.1.8.dist-info/METADATA
shipgit-0.1.8.dist-info/WHEEL
shipgit-0.1.8.dist-info/entry_points.txt
shipgit-0.1.8.dist-info/licenses/LICENSE
shipgit-0.1.8.dist-info/RECORD
