Metadata-Version: 2.1
Name: shipgit
Version: 0.1.8
Summary: simplest command line menu driven deployment tool.  using git, tags, and branches to deploy
Project-URL: Homepage, https://github.com/tsomerville2/shipgit
Project-URL: Issues, https://github.com/tsomerville2/shipgit/issues
Author-email: Travis Somerville <travis.somerville@gmail.com>
License-File: LICENSE
Classifier: License :: OSI Approved :: MIT License
Classifier: Operating System :: OS Independent
Classifier: Programming Language :: Python :: 3
Requires-Python: >=3.8
